unioncom/Model.py
unioncom/UnionCom.py
unioncom/__init__.py
unioncom/test.py
unioncom/utils.py
unioncom/visualization.py
unioncom-0.4.0.dist-info/LICENSE.txt
unioncom-0.4.0.dist-info/METADATA
unioncom-0.4.0.dist-info/WHEEL
unioncom-0.4.0.dist-info/top_level.txt
unioncom-0.4.0.dist-info/RECORD
