Metadata-Version: 2.1
Name: unioncom
Version: 0.4.0
Summary: unioncom: multimodal data integration method
Home-page: https://github.com/caokai1073/unioncom
Author: caokai
Author-email: caokai@amss.ac.cn
License: MIT Licence
Keywords: unioncom,caokai,amss
Platform: any
Requires-Python: >=3.6
